jax_fdm/__init__.py
jax_fdm/__main__.py
jax_fdm/constraints/__init__.py
jax_fdm/constraints/constraint.py
jax_fdm/constraints/edge/__init__.py
jax_fdm/constraints/edge/angle.py
jax_fdm/constraints/edge/edge.py
jax_fdm/constraints/edge/force.py
jax_fdm/constraints/edge/length.py
jax_fdm/constraints/network/__init__.py
jax_fdm/constraints/network/force.py
jax_fdm/constraints/network/length.py
jax_fdm/constraints/network/network.py
jax_fdm/constraints/node/__init__.py
jax_fdm/constraints/node/coordinates.py
jax_fdm/constraints/node/curvature.py
jax_fdm/constraints/node/node.py
jax_fdm/constraints/node/normal.py
jax_fdm/constraints/node/tangent.py
jax_fdm/constraints/vertex/__init__.py
jax_fdm/constraints/vertex/coordinates.py
jax_fdm/constraints/vertex/vertex.py
jax_fdm/datastructures/__init__.py
jax_fdm/datastructures/datastructure.py
jax_fdm/datastructures/mesh.py
jax_fdm/datastructures/network.py
jax_fdm/equilibrium/__init__.py
jax_fdm/equilibrium/fdm.py
jax_fdm/equilibrium/loads.py
jax_fdm/equilibrium/models.py
jax_fdm/equilibrium/sparse.py
jax_fdm/equilibrium/states.py
jax_fdm/equilibrium/solvers/__init__.py
jax_fdm/equilibrium/solvers/fixed_point.py
jax_fdm/equilibrium/solvers/jaxopt.py
jax_fdm/equilibrium/solvers/least_squares.py
jax_fdm/equilibrium/solvers/nonlinear.py
jax_fdm/equilibrium/solvers/optimistix.py
jax_fdm/equilibrium/solvers/root_finding.py
jax_fdm/equilibrium/structures/__init__.py
jax_fdm/equilibrium/structures/graphs.py
jax_fdm/equilibrium/structures/meshes.py
jax_fdm/equilibrium/structures/mixins.py
jax_fdm/equilibrium/structures/structures.py
jax_fdm/geometry/__init__.py
jax_fdm/geometry/geometry.py
jax_fdm/goals/__init__.py
jax_fdm/goals/abstract_goal.py
jax_fdm/goals/goal.py
jax_fdm/goals/helpers.py
jax_fdm/goals/state.py
jax_fdm/goals/edge/__init__.py
jax_fdm/goals/edge/angle.py
jax_fdm/goals/edge/direction.py
jax_fdm/goals/edge/edge.py
jax_fdm/goals/edge/force.py
jax_fdm/goals/edge/length.py
jax_fdm/goals/edge/loadpath.py
jax_fdm-0.9.0.dist-info/licenses/AUTHORS.md
jax_fdm-0.9.0.dist-info/licenses/LICENSE
jax_fdm-0.9.0.dist-info/METADATA
jax_fdm-0.9.0.dist-info/WHEEL
jax_fdm-0.9.0.dist-info/top_level.txt
jax_fdm-0.9.0.dist-info/RECORD
