Metadata-Version: 2.4
Name: jax_fdm
Version: 0.9.0
Summary: Auto-differentiable and hardware-accelerated force density method
Home-page: https://github.com/arpastrana/jax_fdm
Author: Rafael Pastrana
Author-email: arpastrana@princeton.edu
License: MIT license
Keywords: jax,automatic-differentiation,architecture,form-finding,structural-design
Classifier: Development Status :: 4 - Beta
Classifier: Intended Audience :: Developers
Classifier: Topic :: Scientific/Engineering
Classifier: License :: OSI Approved :: MIT License
Classifier: Operating System :: Unix
Classifier: Operating System :: POSIX
Classifier: Operating System :: Microsoft :: Windows
Classifier: Programming Language :: Python
Classifier: Programming Language :: Python :: 3
Classifier: Programming Language :: Python :: 3.7
Classifier: Programming Language :: Python :: 3.8
Classifier: Programming Language :: Python :: 3.9
Classifier: Programming Language :: Python :: 3.10
Classifier: Programming Language :: Python :: Implementation :: CPython
Requires-Python: >=3.7
License-File: LICENSE
License-File: AUTHORS.md
Requires-Dist: jax[cpu]
Requires-Dist: compas<2.0
Requires-Dist: scipy
Requires-Dist: jaxopt
Requires-Dist: equinox
Requires-Dist: lineax
Requires-Dist: optimistix
Dynamic: author
Dynamic: author-email
Dynamic: classifier
Dynamic: description
Dynamic: description-content-type
Dynamic: home-page
Dynamic: keywords
Dynamic: license
Dynamic: license-file
Dynamic: requires-dist
Dynamic: requires-python
Dynamic: summary
